{
  "testing-library-alpine": {
    "minified": {
      "pretty": "283 B",
      "raw": 283
    },
    "brotli": {
      "pretty": "174 B",
      "raw": 174
    }
  },
  "utilities": {
    "minified": {
      "pretty": "2.19 kB",
      "raw": 2192
    },
    "brotli": {
      "pretty": "821 B",
      "raw": 821
    }
  },
  "vitest-environment-alpine": {
    "minified": {
      "pretty": "47.3 kB",
      "raw": 47260
    },
    "brotli": {
      "pretty": "15.5 kB",
      "raw": 15511
    }
  }
}